polynomial_regression/__init__.py
polynomial_regression/expon.py
polynomial_regression/log.py
polynomial_regression/logistic.py
polynomial_regression/main.py
polynomial_regression/sinusoidal.py
polynomial_regression/train_test.py
polynomial_regression_model-3.1.4.dist-info/METADATA
polynomial_regression_model-3.1.4.dist-info/WHEEL
polynomial_regression_model-3.1.4.dist-info/top_level.txt
polynomial_regression_model-3.1.4.dist-info/RECORD
