Metadata-Version: 2.1
Name: polynomial-regression-model
Version: 3.1.4
Summary: Python package that analyses the given datasets and comes up with the best regression representation with either the smallest polynomial degree possible, to be the most reliable without overfitting or other models such as exponentials and logarithms
Home-page: https://github.com/nikolas-virionis/polynomial-regression
Author: Nikolas B Virionis
Author-email: nikolas.virionis@bandtec.com.br
License: UNKNOWN
Platform: UNKNOWN
Classifier: Programming Language :: Python :: 3
Classifier: Programming Language :: Python :: 3.9
Requires-Dist: matplotlib
Requires-Dist: numpy
Requires-Dist: sklearn
